meshagent/browserbase/agents/__init__.py
meshagent/browserbase/agents/browserbase.py
meshagent_browserbase-0.0.1.dist-info/METADATA
meshagent_browserbase-0.0.1.dist-info/WHEEL
meshagent_browserbase-0.0.1.dist-info/top_level.txt
meshagent_browserbase-0.0.1.dist-info/RECORD
